maglimit/__init__.py
maglimit/limiting_mag.py
maglimit-0.0.2.dist-info/LICENSE
maglimit-0.0.2.dist-info/METADATA
maglimit-0.0.2.dist-info/WHEEL
maglimit-0.0.2.dist-info/top_level.txt
maglimit-0.0.2.dist-info/RECORD
